mercury_db/datastore.py
mercury_db-0.0.1.dist-info/LICENSE
mercury_db-0.0.1.dist-info/METADATA
mercury_db-0.0.1.dist-info/WHEEL
mercury_db-0.0.1.dist-info/top_level.txt
mercury_db-0.0.1.dist-info/RECORD
